[{"rootID": "A", "actionType": "tweet", "parentID": "A", "nodeTime": "2017-08-15T00:00:00Z", "nodeUserID": "a", "nodeID": "A"}, {"rootID": "A", "actionType": "retweet", "parentID": "?", "nodeTime": "2017-08-15T00:00:01Z", "nodeUserID": "b", "nodeID": "B"}, {"rootID": "A", "actionType": "retweet", "parentID": "?", "nodeTime": "2017-08-15T00:00:02Z", "nodeUserID": "c", "nodeID": "C"}, {"rootID": "?", "actionType": "reply", "parentID": "A", "nodeTime": "2017-08-15T00:00:03Z", "nodeUserID": "d", "nodeID": "D"}, {"rootID": "?", "actionType": "reply", "parentID": "D", "nodeTime": "2017-08-15T00:00:04Z", "nodeUserID": "e", "nodeID": "E"}, {"rootID": "A", "actionType": "retweet", "parentID": "?", "nodeTime": "2017-08-15T00:00:05Z", "nodeUserID": "f", "nodeID": "F"}, {"rootID": "?", "actionType": "reply", "parentID": "B", "nodeTime": "2017-08-15T00:00:06Z", "nodeUserID": "g", "nodeID": "G"}, {"rootID": "H", "actionType": "tweet", "parentID": "H", "nodeTime": "2017-08-15T00:00:07Z", "nodeUserID": "h", "nodeID": "H"}, {"rootID": "H", "actionType": "retweet", "parentID": "?", "nodeTime": "2017-08-15T00:00:08Z", "nodeUserID": "i", "nodeID": "I"}, {"rootID": "?", "actionType": "reply", "parentID": "H", "nodeTime": "2017-08-15T00:00:09Z", "nodeUserID": "j", "nodeID": "J"}, {"rootID": "H", "actionType": "retweet", "parentID": "?", "nodeTime": "2017-08-15T00:00:12Z", "nodeUserID": "m", "nodeID": "M"}, {"rootID": "H", "actionType": "retweet", "parentID": "?", "nodeTime": "2017-08-15T00:00:13Z", "nodeUserID": "n", "nodeID": "N"}, {"rootID": "H", "actionType": "retweet", "parentID": "?", "nodeTime": "2017-08-15T00:00:14Z", "nodeUserID": "o", "nodeID": "O"}]